pymordial/__init__.py
pymordial/configs.yaml
pymordial/core/__init__.py
pymordial/core/app.py
pymordial/core/blueprints/__init__.py
pymordial/core/blueprints/bridge_device.py
pymordial/core/blueprints/emulator_device.py
pymordial/core/blueprints/extract_strategy.py
pymordial/core/blueprints/ocr_device.py
pymordial/core/blueprints/vision_device.py
pymordial/core/controller.py
pymordial/core/plugin.py
pymordial/core/registry.py
pymordial/core/screen.py
pymordial/core/state_machine.py
pymordial/py.typed
pymordial/ui/__init__.py
pymordial/ui/element.py
pymordial/ui/image.py
pymordial/ui/pixel.py
pymordial/ui/text.py
pymordial/utils/__init__.py
pymordial/utils/config.py
pymordial/utils/exceptions.py
pymordial-0.4.1.dist-info/WHEEL
pymordial-0.4.1.dist-info/METADATA
pymordial-0.4.1.dist-info/RECORD
