Metadata-Version: 2.3
Name: pymordial
Version: 0.4.1
Summary: An extensible automation framework for Python, designed to support any platform via abstract controllers.
Author: IAmNo1Special
Author-email: IAmNo1Special <ivmno1special@gmail.com>
Classifier: Intended Audience :: Developers
Classifier: License :: OSI Approved :: MIT License
Classifier: Operating System :: Microsoft :: Windows
Classifier: Programming Language :: Python
Classifier: Topic :: Software Development :: Libraries :: Python Modules
Requires-Dist: pyyaml>=6.0.2
Requires-Python: >=3.13
Project-URL: homepage, https://github.com/IAmNo1Special/Pymordial
Project-URL: issues, https://github.com/IAmNo1Special/Pymordial/issues
